{"title":"Darmo Hill","id":"1110","meta":{"name":"Darmo Hill","menu":"darmo-hill-menu","tab_menu":"none","appZip":"https:\/\/myapppresser.com\/gravigodesign\/wp-content\/uploads\/sites\/89\/2017\/06\/darmo-hill-1.7.zip","zipFolder":"85-1110","app_update_version":1,"design":{"toolbar_background":"#725b39","toolbar_color":"","text_color":"#808178","body_bg":"","left_menu_bg":"","left_menu_text":"","left_menu_icons":"","button_text":"#bc9d65","button_background":"","link_color":"#bc9d65","headings_color":"#bc9d65","status_bar_bkg":"","custom_css":""},"light_status_bar":null,"menu_right":null,"rtl":null,"intro_slug":""},"ads":{"ios":{"banner":""},"android":{"banner":""}},"segments":"","languages":"","assets":{"header_logo":""},"menus":{"items":[{"title":"Home","page_id":"1111","page_type":"html","list_route":null,"list_display":null,"favorites":null,"show_slider":"false","slide_route":null,"slug":"home-3","type":"apppages","url":"https:\/\/myapppresser.com\/gravigodesign\/apppages\/home-3\/","extra_classes":"","target":"","class":"","parent_id":"0"},{"title":"Concept","page_id":"1117","page_type":"html","list_route":null,"list_display":null,"favorites":null,"show_slider":"false","slide_route":null,"slug":"dh-concept","type":"apppages","url":"https:\/\/myapppresser.com\/gravigodesign\/apppages\/dh-concept\/","extra_classes":"","target":"","class":"","parent_id":"0"},{"title":"Towers","page_id":"1120","page_type":"html","list_route":null,"list_display":null,"favorites":null,"show_slider":"false","slide_route":null,"slug":"dh-towers","type":"apppages","url":"https:\/\/myapppresser.com\/gravigodesign\/apppages\/dh-towers\/","extra_classes":"","target":"","class":"","parent_id":"0"},{"title":"Facilities","page_id":"1121","page_type":"html","list_route":null,"list_display":null,"favorites":null,"show_slider":"false","slide_route":null,"slug":"dh-facilities","type":"apppages","url":"https:\/\/myapppresser.com\/gravigodesign\/apppages\/dh-facilities\/","extra_classes":"","target":"","class":"","parent_id":"0"},{"title":"Gallery","page_id":"1122","page_type":"html","list_route":null,"list_display":null,"favorites":null,"show_slider":"false","slide_route":null,"slug":"dh-gallery","type":"apppages","url":"https:\/\/myapppresser.com\/gravigodesign\/apppages\/dh-gallery\/","extra_classes":"","target":"","class":"","parent_id":"0"},{"title":"Location","page_id":"1123","page_type":"html","list_route":null,"list_display":null,"favorites":null,"show_slider":"false","slide_route":null,"slug":"dh-location","type":"apppages","url":"https:\/\/myapppresser.com\/gravigodesign\/apppages\/dh-location\/","extra_classes":"hide","target":"","class":"","parent_id":"0"},{"title":"Contact","page_id":"1124","page_type":"html","list_route":null,"list_display":null,"favorites":null,"show_slider":"false","slide_route":null,"slug":"dh-contact","type":"apppages","url":"https:\/\/myapppresser.com\/gravigodesign\/apppages\/dh-contact\/","extra_classes":"hide","target":"","class":"","parent_id":"0"},{"title":"Rosewood","page_id":"1126","page_type":"html","list_route":null,"list_display":null,"favorites":null,"show_slider":"false","slide_route":null,"slug":"dh-rosewood","type":"apppages","url":"https:\/\/myapppresser.com\/gravigodesign\/apppages\/dh-rosewood\/","extra_classes":"hide","target":"","class":"","parent_id":"0"},{"title":"Rosewood Typical Floor","page_id":"1127","page_type":"html","list_route":null,"list_display":null,"favorites":null,"show_slider":"false","slide_route":null,"slug":"dh-rosewood-typical-floor","type":"apppages","url":"https:\/\/myapppresser.com\/gravigodesign\/apppages\/dh-rosewood-typical-floor\/","extra_classes":"hide","target":"","class":"","parent_id":"0"},{"title":"Rosewood Types of Unit","page_id":"1128","page_type":"html","list_route":null,"list_display":null,"favorites":null,"show_slider":"false","slide_route":null,"slug":"dh-rosewood-types-of-unit","type":"apppages","url":"https:\/\/myapppresser.com\/gravigodesign\/apppages\/dh-rosewood-types-of-unit\/","extra_classes":"hide","target":"","class":"","parent_id":"0"}],"name":"Darmo Hill Menu"},"tab_menu":{"items":null,"name":""},"side_menu_login":"","wordpress_url":""}